{ "id": "0000000056789", "title": "Fresh Gala Apple", "brand": "Nature's Harvest", "description": "Fresh Gala Apple. A crisp, sweet, and mild-flavored apple characterized by its signature pink-orange striped skin over a yellow background. Perfect for fresh snacking, slicing into salads, or packing in lunchboxes. Key specifications: Category: Plant based foods and beverages; Quantity: 170 g; Serving size: 1 medium apple (170 g); Nutri-Score: A; NOVA group: 1; Eco-Score: A; Dietary restrictions: vegan, vegetarian; Ingredients analysis: palm-oil-free, vegan, vegetarian; Energy (kcal/100g): 52 kcal; Fat (g/100g): 0.2 g; Saturated fat (g/100g): 0 g; Sugars (g/100g): 10 g; Salt (g/100g): 0 g; Protein (g/100g): 0.3 g; Fiber (g/100g): 2.4 g; Countries: United States", "image_url": "https://alexmarquardt.com/ecommerce-demo-assets/images/groceries/one-apple-001-400x400.png", "price": 0.89, "currency": "USD", "categories": [ "Plant based foods and beverages", "Plant based foods", "Fruits and vegetables" ], "attrs": { "Quantity": "170 g", "Serving size": "1 medium apple (170 g)", "Nutri-Score": "A", "NOVA group": "1", "Eco-Score": "A", "Ingredients analysis": "palm-oil-free, vegan, vegetarian", "Countries": "United States", "Category": "Plant based foods and beverages", "Energy (kcal/100g)": "52 kcal", "Fat (g/100g)": "0.2 g", "Saturated fat (g/100g)": "0 g", "Sugars (g/100g)": "10 g", "Salt (g/100g)": "0 g", "Protein (g/100g)": "0.3 g", "Fiber (g/100g)": "2.4 g", "Dietary restrictions": "vegan, vegetarian", "Price source": "estimated_unit_model", "Pricing bucket": "fresh_produce", "Estimated unit price": "5.23 USD/kg" }, "attr_keys": [ "Category", "Countries", "Dietary restrictions", "Eco-Score", "Energy (kcal/100g)", "Estimated unit price", "Fat (g/100g)", "Fiber (g/100g)", "Ingredients analysis", "NOVA group", "Nutri-Score", "Price source", "Pricing bucket", "Protein (g/100g)", "Quantity", "Salt (g/100g)", "Saturated fat (g/100g)", "Serving size", "Sugars (g/100g)" ], "dietary_restrictions": [ "vegan", "vegetarian" ] }
{ "id": "0000000056790", "title": "Fuji Apples, 3 lb Bag", "brand": "Orchard Fresh", "description": "Fuji Apples, 3 lb Bag. A convenient bulk bag containing firm, extra-sweet Fuji apples known for their dense flesh and long shelf life. These apples are excellent for baking into pies, making homemade applesauce, or juicing. Key specifications: Category: Plant based foods and beverages; Quantity: 3 lb; Serving size: 1 apple (150 g); Nutri-Score: A; NOVA group: 1; Eco-Score: A; Dietary restrictions: vegan, vegetarian; Ingredients analysis: palm-oil-free, vegan, vegetarian; Energy (kcal/100g): 52 kcal; Fat (g/100g): 0.2 g; Saturated fat (g/100g): 0 g; Sugars (g/100g): 11 g; Salt (g/100g): 0 g; Protein (g/100g): 0.3 g; Fiber (g/100g): 2.1 g; Countries: United States", "image_url": "https://alexmarquardt.com/ecommerce-demo-assets/images/groceries/bag-of-apples-001-400x400.png", "price": 4.99, "currency": "USD", "categories": [ "Plant based foods and beverages", "Plant based foods", "Fruits and vegetables" ], "attrs": { "Quantity": "3 lb", "Serving size": "1 apple (150 g)", "Nutri-Score": "A", "NOVA group": "1", "Eco-Score": "A", "Ingredients analysis": "palm-oil-free, vegan, vegetarian", "Countries": "United States", "Category": "Plant based foods and beverages", "Energy (kcal/100g)": "52 kcal", "Fat (g/100g)": "0.2 g", "Saturated fat (g/100g)": "0 g", "Sugars (g/100g)": "11 g", "Salt (g/100g)": "0 g", "Protein (g/100g)": "0.3 g", "Fiber (g/100g)": "2.1 g", "Dietary restrictions": "vegan, vegetarian", "Price source": "estimated_unit_model", "Pricing bucket": "fresh_produce", "Estimated unit price": "3.66 USD/kg" }, "attr_keys": [ "Category", "Countries", "Dietary restrictions", "Eco-Score", "Energy (kcal/100g)", "Estimated unit price", "Fat (g/100g)", "Fiber (g/100g)", "Ingredients analysis", "NOVA group", "Nutri-Score", "Price source", "Pricing bucket", "Protein (g/100g)", "Quantity", "Salt (g/100g)", "Saturated fat (g/100g)", "Serving size", "Sugars (g/100g)" ], "dietary_restrictions": [ "vegan", "vegetarian" ] }